mrtracker/__init__.py
mrtracker/__main__.py
mrtracker/app.py
mrtracker/config.py
mrtracker/createdb.sql
mrtracker/db.py
mrtracker/default_config.json
mrtracker/mode.py
mrtracker/stopwatch.py
mrtracker/views/help_view.py
mrtracker/views/main_view.py
mrtracker/widgets/__init__.py
mrtracker/widgets/current_task.py
mrtracker/widgets/entry.py
mrtracker/widgets/header.py
mrtracker/widgets/in_app_logger.py
mrtracker/widgets/nested_list.py
mrtracker/widgets/simple_scrollview.py
mrtracker/widgets/tasklist.py
mrtracker/widgets/text_input.py
mrtracker/widgets/timer.py
mrtracker-0.1.1.dist-info/entry_points.txt
mrtracker-0.1.1.dist-info/LICENSE
mrtracker-0.1.1.dist-info/WHEEL
mrtracker-0.1.1.dist-info/METADATA
mrtracker-0.1.1.dist-info/RECORD
